README.md
setup.cfg
setup.py
acnaweblib/__init__.py
acnaweblib/calculator.py
acnaweblib.egg-info/PKG-INFO
acnaweblib.egg-info/SOURCES.txt
acnaweblib.egg-info/dependency_links.txt
acnaweblib.egg-info/top_level.txt