Metadata-Version: 2.1
Name: acnaweblib
Version: 0.1.19
Home-page: https://github.com/acnaweb/acnaweblib
Author: Antonio Carlos de Lima Junior
Author-email: antonioclj.ac@gmail.com
License: MIT
Keywords: library test
Classifier: Development Status :: 5 - Production/Stable
Classifier: Programming Language :: Python :: 3
Classifier: Operating System :: OS Independent
Classifier: Natural Language :: Portuguese (Brazilian)
Classifier: Natural Language :: English
